ujbk2/__init__.py
ujbk2/one_plus_one.py
ujbk2-0.0.4.dist-info/METADATA
ujbk2-0.0.4.dist-info/WHEEL
ujbk2-0.0.4.dist-info/top_level.txt
ujbk2-0.0.4.dist-info/RECORD
